<?xml version="1.0" encoding="utf-8"?>
<anime-set-list>
  <set>
    <titles>
      <title type="main" xml:lang="x-jat">Studio Ghibli Collection</title>
    </titles>
  </set>
  <set>
    <titles>
      <title type="main" xml:lang="x-jat">Initial D Collection</title>
    </titles>
  </set>
  <set>
    <titles>
      <title type="main" xml:lang="x-jat">Blood: The Last Vampire Collection</title>
    </titles>
  </set>
  <set>
    <titles>
      <title type="main" xml:lang="x-jat">Devilman Collection</title>
    </titles>
  </set>
  <set>
    <titles>
      <title type="main" xml:lang="x-jat">Koukaku Kidoutai Collection</title>
      <title type="official" xml:lang="en">Ghost in the Shell Collection</title>
    </titles>
  </set>
  <set>
    <titles>
      <title type="main" xml:lang="x-jat">Vampire Hunter D Collection</title>
    </titles>
  </set>
  <set>
    <titles>
      <title type="main" xml:lang="x-jat">Slayers Collection</title>
    </titles>
  </set>
  <set>
    <titles>
      <title type="main" xml:lang="x-jat">Appleseed Collection</title>
    </titles>
  </set>
  <set>
    <titles>
      <title type="main" xml:lang="x-jat">Shinseiki Evangelion Collection</title>
      <title type="official" xml:lang="en">Neon Genesis Evangelion Collection</title>
    </titles>
  </set>
  <set>
    <titles>
      <title type="main" xml:lang="x-jat">Hokuto no Ken Collection</title>
      <title type="official" xml:lang="en">Fist of the North Star Collection</title>
    </titles>
  </set>
  <set>
    <titles>
      <title type="main" xml:lang="x-jat">Garou Densetsu Collection</title>
      <title type="official" xml:lang="en">Fatal Fury Collection</title>
    </titles>
  </set>
  <set>
    <titles>
      <title type="main" xml:lang="x-jat">Armitage III Collection</title>
    </titles>
  </set>
  <set>
    <titles>
      <title type="main" xml:lang="x-jat">Inuyasha Collection</title>
    </titles>
  </set>
  <set>
    <titles>
      <title type="main" xml:lang="x-jat">Project A-Ko Collection</title>
    </titles>
  </set>
  <set>
    <titles>
      <title type="main" xml:lang="x-jat">Kimagure Orange Road Collection</title>
    </titles>
  </set>
  <set>
    <titles>
      <title type="main" xml:lang="x-jat">Meitantei Conan Collection</title>
      <title type="official" xml:lang="en">Case Closed Collection</title>
    </titles>
  </set>
  <set>
    <titles>
      <title type="main" xml:lang="x-jat">Street Fighter Collection</title>
    </titles>
  </set>
  <set>
    <titles>
      <title type="main" xml:lang="x-jat">Lupin Sansei Collection</title>
      <title type="official" xml:lang="en">Lupin III Collection</title>
    </titles>
  </set>
  <set>
    <titles>
      <title type="main" xml:lang="x-jat">Tenchi Muyou! Collection</title>
      <title type="official" xml:lang="en">Tenchi Muyo Collection</title>
    </titles>
  </set>
  <set>
    <titles>
      <title type="main" xml:lang="x-jat">Ranma 1/2 Collection</title>
    </titles>
  </set>
  <set>
    <titles>
      <title type="main" xml:lang="x-jat">Nadesico Collection</title>
    </titles>
  </set>
  <set>
    <titles>
      <title type="main" xml:lang="x-jat">Urusei Yatsura Collection</title>
    </titles>
  </set>
  <set>
    <titles>
      <title type="main" xml:lang="x-jat">Kidou Keisatsu Patlabor Collection</title>
      <title type="official" xml:lang="en">Mobile Police Patlabor Collection</title>
    </titles>
  </set>
  <set>
    <titles>
      <title type="main" xml:lang="x-jat">Dragon Ball Z Collection</title>
    </titles>
  </set>
  <set>
    <titles>
      <title type="main" xml:lang="x-jat">One Piece Collection</title>
    </titles>
  </set>
  <set>
    <titles>
      <title type="main" xml:lang="x-jat">Sakura Taisen Collection</title>
      <title type="official" xml:lang="en">Sakura Wars Collection</title>
    </titles>
  </set>
  <set>
    <titles>
      <title type="main" xml:lang="x-jat">eX-Driver Collection</title>
    </titles>
  </set>
  <set>
    <titles>
      <title type="main" xml:lang="x-jat">Vandread Collection</title>
    </titles>
  </set>
  <set>
    <titles>
      <title type="main" xml:lang="x-jat">Ginga Tetsudou 999 Collection</title>
      <title type="official" xml:lang="en">Galaxy Express 999 Collection</title>
    </titles>
  </set>
  <set>
    <titles>
      <title type="main" xml:lang="x-jat">Maison Ikkoku Collection</title>
    </titles>
  </set>
  <set>
    <titles>
      <title type="main" xml:lang="x-jat">Choujikuu Yousai Macross Collection</title>
      <title type="official" xml:lang="en">Super Dimension Fortress Macross Collection</title>
    </titles>
  </set>
  <set>
    <titles>
      <title type="main" xml:lang="x-jat">Cardcaptor Sakura Collection</title>
    </titles>
  </set>
  <set>
    <titles>
      <title type="main" xml:lang="x-jat">Panda Kopanda Collection</title>
      <title type="official" xml:lang="en">Panda! Go Panda! Collection</title>
    </titles>
  </set>
  <set>
    <titles>
      <title type="main" xml:lang="x-jat">Taiho Shichau zo Collection</title>
      <title type="official" xml:lang="en">You're Under Arrest Collection</title>
    </titles>
  </set>
  <set>
    <titles>
      <title type="main" xml:lang="x-jat">RahXephon Collection</title>
    </titles>
  </set>
  <set>
    <titles>
      <title type="main" xml:lang="x-jat">Kidou Senshi Gundam Collection</title>
      <title type="official" xml:lang="en">Mobile Suit Gundam Collection</title>
    </titles>
  </set>
  <set>
    <titles>
      <title type="main" xml:lang="x-jat">Hadashi no Gen Collection</title>
      <title type="official" xml:lang="en">Barefoot Gen Collection</title>
    </titles>
  </set>
  <set>
    <titles>
      <title type="main" xml:lang="x-jat">Black Jack Collection</title>
    </titles>
  </set>
  <set>
    <titles>
      <title type="main" xml:lang="x-jat">Slam Dunk Collection</title>
    </titles>
  </set>
  <set>
    <titles>
      <title type="main" xml:lang="x-jat">Captain Harlock Collection</title>
    </titles>
  </set>
  <set>
    <titles>
      <title type="main" xml:lang="x-jat">Munto Collection</title>
    </titles>
  </set>
  <set>
    <titles>
      <title type="main" xml:lang="x-jat">Yuu Yuu Hakusho Collection</title>
      <title type="official" xml:lang="en">Yu Yu Hakusho Collection</title>
    </titles>
  </set>
  <set>
    <titles>
      <title type="main" xml:lang="x-jat">Gall Force Collection</title>
    </titles>
  </set>
  <set>
    <titles>
      <title type="main" xml:lang="x-jat">Mak Dau Collection</title>
    </titles>
  </set>
  <set>
    <titles>
      <title type="main" xml:lang="x-jat">Rumic World Collection</title>
    </titles>
  </set>
  <set>
    <titles>
      <title type="main" xml:lang="x-jat">Candy Candy Collection</title>
    </titles>
  </set>
  <set>
    <titles>
      <title type="main" xml:lang="x-jat">Crayon Shin-chan Collection</title>
    </titles>
  </set>
  <set>
    <titles>
      <title type="main" xml:lang="x-jat">Pocket Monsters Collection</title>
      <title type="official" xml:lang="en">Pokemon Collection</title>
    </titles>
  </set>
  <set>
    <titles>
      <title type="main" xml:lang="x-jat">Touch Collection</title>
    </titles>
  </set>
  <set>
    <titles>
      <title type="main" xml:lang="x-jat">Sengoku Majin Goushougun Collection</title>
    </titles>
  </set>
  <set>
    <titles>
      <title type="main" xml:lang="x-jat">Rokushin Gattai GodMars Collection</title>
      <title type="official" xml:lang="en">God Mars	Collection</title>
    </titles>
  </set>
  <set>
    <titles>
      <title type="main" xml:lang="x-jat">Violence Jack Collection</title>
    </titles>
  </set>
  <set>
    <titles>
      <title type="main" xml:lang="x-jat">Dirty Pair Collection</title>
    </titles>
  </set>
  <set>
    <titles>
      <title type="main" xml:lang="x-jat">Sweat Punch Collection</title>
    </titles>
  </set>
  <set>
    <titles>
      <title type="main" xml:lang="x-jat">Golgo 13 Collection</title>
    </titles>
  </set>
  <set>
    <titles>
      <title type="main" xml:lang="x-jat">Dragon Ball Collection</title>
    </titles>
  </set>
  <set>
    <titles>
      <title type="main" xml:lang="x-jat">.hack// Collection</title>
    </titles>
  </set>
  <set>
    <titles>
      <title type="main" xml:lang="x-jat">Digimon Adventure Collection</title>
    </titles>
  </set>
  <set>
    <titles>
      <title type="main" xml:lang="x-jat">Final Fantasy VII Collection</title>
    </titles>
  </set>
  <set>
    <titles>
      <title type="main" xml:lang="x-jat">Kidou Senshi SD Gundam Collection</title>
      <title type="official" xml:lang="en">Mobile Suit SD Gundam Collection</title>
    </titles>
  </set>
  <set>
    <titles>
      <title type="main" xml:lang="x-jat">Digimon Tamers Collection</title>
    </titles>
  </set>
  <set>
    <titles>
      <title type="main" xml:lang="x-jat">Sangokushi Collection</title>
      <title type="official" xml:lang="en">Romance of the Three Kingdoms Collection</title>
    </titles>
  </set>
  <set>
    <titles>
      <title type="main" xml:lang="x-jat">Unico Collection</title>
    </titles>
  </set>
  <set>
    <titles>
      <title type="main" xml:lang="x-jat">Nasu Collection</title>
    </titles>
  </set>
  <set>
    <titles>
      <title type="main" xml:lang="x-jat">Ginga Eiyuu Densetsu Collection</title>
      <title type="official" xml:lang="en">Legend of Galactic Heroes Collection</title>
    </titles>
  </set>
  <set>
    <titles>
      <title type="main" xml:lang="x-jat">Hi no Tori Collection</title>
      <title type="official" xml:lang="en">Phoenix Collection</title>
    </titles>
  </set>
  <set>
    <titles>
      <title type="main" xml:lang="x-jat">Chibi Maruko-chan Collection</title>
    </titles>
  </set>
  <set>
    <titles>
      <title type="main" xml:lang="x-jat">Junkers Come Here Collection</title>
    </titles>
  </set>
  <set>
    <titles>
      <title type="main" xml:lang="x-jat">Saint Seiya Collection</title>
    </titles>
  </set>
  <set>
    <titles>
      <title type="main" xml:lang="x-jat">Dengeki Oshioki Musume Gotaman Collection</title>
      <title type="official" xml:lang="en">Butt Attack Punisher Girl Gotaman Collection</title>
    </titles>
  </set>
  <set>
    <titles>
      <title type="main" xml:lang="x-jat">Naruto Collection</title>
    </titles>
  </set>
  <set>
    <titles>
      <title type="main" xml:lang="x-jat">Soukihei MD Geist Collection</title>
      <title type="official" xml:lang="en">M.D. Geist Collection</title>
    </titles>
  </set>
  <set>
    <titles>
      <title type="main" xml:lang="x-jat">Jungle Taitei Collection</title>
      <title type="official" xml:lang="en">Jungle Emperor Collection</title>
    </titles>
  </set>
  <set>
    <titles>
      <title type="main" xml:lang="x-jat">Tetsuwan Atom Collection</title>
      <title type="official" xml:lang="en">Astro Boy Collection</title>
    </titles>
  </set>
  <set>
    <titles>
      <title type="main" xml:lang="x-jat">City Hunter Collection</title>
    </titles>
  </set>
  <set>
    <titles>
      <title type="main" xml:lang="x-jat">Yuu Gi Ou Collection</title>
      <title type="official" xml:lang="en">Yu-Gi-Oh! Collection</title>
    </titles>
  </set>
  <set>
    <titles>
      <title type="main" xml:lang="x-jat">Ashita no Joe Collection</title>
      <title type="official" xml:lang="en">Tomorrow's Joe Collection</title>
    </titles>
  </set>
  <set>
    <titles>
      <title type="main" xml:lang="x-jat">Tottoko Hamtarou Collection</title>
      <title type="official" xml:lang="en">Hamtaro Collection</title>
    </titles>
  </set>
  <set>
    <titles>
      <title type="main" xml:lang="x-jat">Konjiki no Gash Bell!! Collection</title>
      <title type="official" xml:lang="en">Zatch Bell! Collection</title>
    </titles>
  </set>
  <set>
    <titles>
      <title type="main" xml:lang="x-jat">Ikkyuu-san Collection</title>
    </titles>
  </set>
  <set>
    <titles>
      <title type="main" xml:lang="x-jat">Ninkuu Collection</title>
    </titles>
  </set>
  <set>
    <titles>
      <title type="main" xml:lang="x-jat">Choujin Locke Collection</title>
      <title type="official" xml:lang="en">Locke the Superman Collection</title>
    </titles>
  </set>
  <set>
    <titles>
      <title type="main" xml:lang="x-jat">Ojamajo Doremi Collection</title>
    </titles>
  </set>
  <set>
    <titles>
      <title type="main" xml:lang="x-jat">Densetsu Kyojin Ideon Collection</title>
      <title type="official" xml:lang="en">Space Runaway Ideon Collection</title>
    </titles>
  </set>
  <set>
    <titles>
      <title type="main" xml:lang="x-jat">Kochira Katsushikaku Kameari Kouenmae Hashutsujo Collection</title>
    </titles>
  </set>
  <set>
    <titles>
      <title type="main" xml:lang="x-jat">Mahou no Tenshi Creamy Mami Collection</title>
    </titles>
  </set>
  <set>
    <titles>
      <title type="main" xml:lang="x-jat">Himitsu no Akko-chan Collection</title>
    </titles>
  </set>
  <set>
    <titles>
      <title type="main" xml:lang="x-jat">Wakusei Robo Danguard Ace Collection</title>
      <title type="official" xml:lang="en">Danguard Ace Collection</title>
    </titles>
  </set>
  <set>
    <titles>
      <title type="main" xml:lang="x-jat">Doraemon Collection</title>
    </titles>
  </set>
  <set>
    <titles>
      <title type="main" xml:lang="x-jat">Uchuu Senkan Yamato Collection</title>
      <title type="official" xml:lang="en">Space Battleship Yamato Collection</title>
    </titles>
  </set>
  <set>
    <titles>
      <title type="main" xml:lang="x-jat">Maple Town Monogatari Collection</title>
      <title type="official" xml:lang="en">Maple Town Stories Collection</title>
    </titles>
  </set>
  <set>
    <titles>
      <title type="main" xml:lang="x-jat">Magical Taruruuto-kun Collection</title>
    </titles>
  </set>
  <set>
    <titles>
      <title type="main" xml:lang="x-jat">Jigoku Sensei Nube Collection</title>
      <title type="official" xml:lang="en">Hell Teacher Nube Collection</title>
    </titles>
  </set>
  <set>
    <titles>
      <title type="main" xml:lang="x-jat">Kinnikuman Collection</title>
    </titles>
  </set>
  <set>
    <titles>
      <title type="main" xml:lang="x-jat">Bishoujo Senshi Sailor Moon Collection</title>
      <title type="official" xml:lang="en">Sailor Moon Collection</title>
    </titles>
  </set>
  <set>
    <titles>
      <title type="main" xml:lang="x-jat">Cyborg 009 Collection</title>
    </titles>
  </set>
  <set>
    <titles>
      <title type="main" xml:lang="x-jat">Nagagutsu Collection</title>
    </titles>
  </set>
  <set>
    <titles>
      <title type="main" xml:lang="x-jat">Sekai Meisaku Douwa Collection</title>
    </titles>
  </set>
  <set>
    <titles>
      <title type="main" xml:lang="x-jat">Dr. Slump Collection</title>
    </titles>
  </set>
  <set>
    <titles>
      <title type="main" xml:lang="x-jat">Gegege no Kitarou Collection</title>
    </titles>
  </set>
  <set>
    <titles>
      <title type="main" xml:lang="x-jat">Silent Mobius Collection</title>
    </titles>
  </set>
  <set>
    <titles>
      <title type="main" xml:lang="x-jat">Captain Tsubasa Collection</title>
    </titles>
  </set>
  <set>
    <titles>
      <title type="main" xml:lang="x-jat">Taiyou no Kiba Dagram Collection</title>
    </titles>
  </set>
  <set>
    <titles>
      <title type="main" xml:lang="x-jat">Hagane no Renkinjutsushi Collection</title>
      <title type="official" xml:lang="en">Fullmetal Alchemist Collection</title>
    </titles>
  </set>
  <set>
    <titles>
      <title type="main" xml:lang="x-jat">Ginga Hyouryuu Vifam Collection</title>
    </titles>
  </set>
  <set>
    <titles>
      <title type="main" xml:lang="x-jat">Tennis no Ouji-sama Collection</title>
      <title type="official" xml:lang="en">The Prince of Tennis Collection</title>
    </titles>
  </set>
  <set>
    <titles>
      <title type="main" xml:lang="x-jat">Hashire Melos Collection</title>
      <title type="official" xml:lang="en">Run Melos! Collection</title>
    </titles>
  </set>
  <set>
    <titles>
      <title type="main" xml:lang="x-jat">Ninja Hattori-kun Collection</title>
    </titles>
  </set>
  <set>
    <titles>
      <title type="main" xml:lang="x-jat">Kino no Tabi Collection</title>
      <title type="official" xml:lang="en">Kino's Journey Collection</title>
    </titles>
  </set>
  <set>
    <titles>
      <title type="main" xml:lang="x-jat">Futari wa Precure Collection</title>
      <title type="official" xml:lang="en">Pretty Cure Collection</title>
    </titles>
  </set>
  <set>
    <titles>
      <title type="main" xml:lang="x-jat">Yawara! Collection</title>
    </titles>
  </set>
  <set>
    <titles>
      <title type="main" xml:lang="x-jat">Tekkon Kinkreet Collection</title>
    </titles>
  </set>
  <set>
    <titles>
      <title type="main" xml:lang="x-jat">Turn A Gundam Collection</title>
    </titles>
  </set>
  <set>
    <titles>
      <title type="main" xml:lang="x-jat">Duel Masters Collection</title>
    </titles>
  </set>
  <set>
    <titles>
      <title type="main" xml:lang="x-jat">Beast Wars Collection</title>
    </titles>
  </set>
  <set>
    <titles>
      <title type="main" xml:lang="x-jat">Kero Kero Keroppi Collection</title>
    </titles>
  </set>
  <set>
    <titles>
      <title type="main" xml:lang="x-jat">Gamba no Bouken Collection</title>
    </titles>
  </set>
  <set>
    <titles>
      <title type="main" xml:lang="x-jat">Ganbare!! Tabuchi-kun!! Collection</title>
    </titles>
  </set>
  <set>
    <titles>
      <title type="main" xml:lang="x-jat">Nine Collection</title>
    </titles>
  </set>
  <set>
    <titles>
      <title type="main" xml:lang="x-jat">Storm Rider Collection</title>
    </titles>
  </set>
  <set>
    <titles>
      <title type="main" xml:lang="x-jat">Chouon Senshi Borgman Collection</title>
      <title type="official" xml:lang="en">Sonic Soldier Borgman Collection</title>
    </titles>
  </set>
  <set>
    <titles>
      <title type="main" xml:lang="x-jat">Animerama Collection</title>
    </titles>
  </set>
  <set>
    <titles>
      <title type="main" xml:lang="x-jat">Licca-chan Collection</title>
    </titles>
  </set>
  <set>
    <titles>
      <title type="main" xml:lang="x-jat">Koukaku Kidoutai Stand Alone Complex Collection</title>
      <title type="official" xml:lang="en">Ghost in the Shell Stand Alone Complex Collection</title>
    </titles>
  </set>
  <set>
    <titles>
      <title type="main" xml:lang="x-jat">Sensou Douwa Collection</title>
      <title type="official" xml:lang="en">War Story Collection</title>
    </titles>
  </set>
  <set>
    <titles>
      <title type="main" xml:lang="x-jat">Keroro Gunsou Collection</title>
      <title type="official" xml:lang="en">Sgt. Frog Collection</title>
    </titles>
  </set>
  <set>
    <titles>
      <title type="main" xml:lang="x-jat">Atashin'chi Collection</title>
      <title type="official" xml:lang="en">My Family Collection</title>
    </titles>
  </set>
  <set>
    <titles>
      <title type="main" xml:lang="x-jat">Lion Books Collection</title>
    </titles>
  </set>
  <set>
    <titles>
      <title type="main" xml:lang="x-jat">Anime Sanjuushi Collection</title>
      <title type="official" xml:lang="en">The Three Musketeers Collection</title>
    </titles>
  </set>
  <set>
    <titles>
      <title type="main" xml:lang="x-jat">Nintama Rantarou Collection</title>
      <title type="official" xml:lang="en">Ninja Boy Rantaro Collection</title>
    </titles>
  </set>
  <set>
    <titles>
      <title type="main" xml:lang="x-jat">Nora Collection</title>
    </titles>
  </set>
  <set>
    <titles>
      <title type="main" xml:lang="x-jat">Riki-Ou Collection</title>
      <title type="official" xml:lang="en">Riki-Oh Collection</title>
    </titles>
  </set>
  <set>
    <titles>
      <title type="main" xml:lang="x-jat">Mahou no Princess Minky Momo Collection</title>
    </titles>
  </set>
  <set>
    <titles>
      <title type="main" xml:lang="x-jat">Beyblade Collection</title>
    </titles>
  </set>
  <set>
    <titles>
      <title type="main" xml:lang="x-jat">Haruka Naru Toki no Naka de Collection</title>
      <title type="official" xml:lang="en">Haruka -Beyond the Stream of Time- Collection</title>
    </titles>
  </set>
  <set>
    <titles>
      <title type="main" xml:lang="x-jat">Sun Ukun Collection</title>
    </titles>
  </set>
  <set>
    <titles>
      <title type="main" xml:lang="x-jat">Kabutomushi Ouja Mushiking Collection</title>
      <title type="official" xml:lang="en">Mushiking Collection</title>
    </titles>
  </set>
  <set>
    <titles>
      <title type="main" xml:lang="x-jat">Kidou Senshi Gundam SEED Collection</title>
      <title type="official" xml:lang="en">Mobile Suit Gundam SEED Collection</title>
    </titles>
  </set>
  <set>
    <titles>
      <title type="main" xml:lang="x-jat">Naniwa Yuukyouden Collection</title>
    </titles>
  </set>
  <set>
    <titles>
      <title type="main" xml:lang="x-jat">Koufuku no Kagaku Collection</title>
      <title type="official" xml:lang="en">Happy Science Collection</title>
    </titles>
  </set>
  <set>
    <titles>
      <title type="main" xml:lang="x-jat">Kaiketsu Zorori Collection</title>
    </titles>
  </set>
  <set>
    <titles>
      <title type="main" xml:lang="x-jat">Bleach Collection</title>
    </titles>
  </set>
  <set>
    <titles>
      <title type="main" xml:lang="x-jat">Top o Nerae! Collection</title>
      <title type="official" xml:lang="en">Gunbuster Collection</title>
    </titles>
  </set>
  <set>
    <titles>
      <title type="main" xml:lang="x-jat">Strike Witches Collection</title>
    </titles>
  </set>
  <set>
    <titles>
      <title type="main" xml:lang="x-jat">Mirai Shounen Conan Collection</title>
      <title type="official" xml:lang="en">Future Boy Conan Collection</title>
    </titles>
  </set>
  <set>
    <titles>
      <title type="main" xml:lang="x-jat">Digimon Savers Collection</title>
    </titles>
  </set>
  <set>
    <titles>
      <title type="main" xml:lang="x-jat">Soukou Kihei Votoms Collection</title>
      <title type="official" xml:lang="en">Armored Trooper Votoms Collection</title>
    </titles>
  </set>
  <set>
    <titles>
      <title type="main" xml:lang="x-jat">Futari wa Precure Splash Star Collection</title>
      <title type="official" xml:lang="en">Pretty Cure Splash Star Collection</title>
    </titles>
  </set>
  <set>
    <titles>
      <title type="main" xml:lang="x-jat">Evangelion Shin Collection</title>
      <title type="official" xml:lang="en">Rebuild of Evangelion Collection</title>
    </titles>
  </set>
  <set>
    <titles>
      <title type="main" xml:lang="x-jat">11 Piki no Neko Collection</title>
      <title type="official" xml:lang="en">Eleven Cats Collection</title>
    </titles>
  </set>
  <set>
    <titles>
      <title type="main" xml:lang="x-jat">Bavi Stock Collection</title>
    </titles>
  </set>
  <set>
    <titles>
      <title type="main" xml:lang="x-jat">Superflat Collection</title>
    </titles>
  </set>
  <set>
    <titles>
      <title type="main" xml:lang="x-jat">Kiddy Grade Collection</title>
    </titles>
  </set>
  <set>
    <titles>
      <title type="main" xml:lang="x-jat">Naruto Shippuuden Collection</title>
    </titles>
  </set>
  <set>
    <titles>
      <title type="main" xml:lang="x-jat">Crows Collection</title>
    </titles>
  </set>
  <set>
    <titles>
      <title type="main" xml:lang="x-jat">Anime Tenchou Collection</title>
    </titles>
  </set>
  <set>
    <titles>
      <title type="main" xml:lang="x-jat">Mahou no Star Magical Emi Collection</title>
    </titles>
  </set>
  <set>
    <titles>
      <title type="main" xml:lang="x-jat">Ookami Shounen Ken Collection</title>
    </titles>
  </set>
  <set>
    <titles>
      <title type="main" xml:lang="x-jat">Yes! Precure 5 Collection</title>
      <title type="official" xml:lang="en">Yes! Pretty Cure 5 Collection</title>
    </titles>
  </set>
  <set>
    <titles>
      <title type="main" xml:lang="x-jat">Tengen Toppa Gurren Lagann Collection</title>
      <title type="official" xml:lang="en">Gurren Lagann Collection</title>
    </titles>
  </set>
  <set>
    <titles>
      <title type="main" xml:lang="x-jat">Sore Ike! Anpanman Collection</title>
    </titles>
  </set>
  <set>
    <titles>
      <title type="main" xml:lang="x-jat">Utsu no Miko Collection</title>
    </titles>
  </set>
  <set>
    <titles>
      <title type="main" xml:lang="x-jat">Major Collection</title>
    </titles>
  </set>
  <set>
    <titles>
      <title type="main" xml:lang="x-jat">Eureka Seven Collection</title>
    </titles>
  </set>
  <set>
    <titles>
      <title type="main" xml:lang="x-jat">Norakuro Collection</title>
    </titles>
  </set>
  <set>
    <titles>
      <title type="main" xml:lang="x-jat">Momotarou Collection</title>
    </titles>
  </set>
  <set>
    <titles>
      <title type="main" xml:lang="x-jat">What's Michael? Collection</title>
    </titles>
  </set>
  <set>
    <titles>
      <title type="main" xml:lang="x-jat">Mahou Shoujo Lyrical Nanoha Collection</title>
      <title type="official" xml:lang="en">Magical Girl Lyrical Nanoha Collection</title>
    </titles>
  </set>
  <set>
    <titles>
      <title type="main" xml:lang="x-jat">Biohazard Collection</title>
    </titles>
  </set>
  <set>
    <titles>
      <title type="main" xml:lang="x-jat">Yurumates Collection</title>
    </titles>
  </set>
  <set>
    <titles>
      <title type="main" xml:lang="x-jat">Hayate no Gotoku Collection</title>
    </titles>
  </set>
  <set>
    <titles>
      <title type="main" xml:lang="x-jat">Precure All Stars Collection</title>
      <title type="official" xml:lang="en">Pretty Cure All Stars Collection</title>
    </titles>
  </set>
  <set>
    <titles>
      <title type="main" xml:lang="x-jat">Himitsukessha Taka no Tsume Collection</title>
    </titles>
  </set>
  <set>
    <titles>
      <title type="main" xml:lang="x-jat">Tamagotchi Collection</title>
    </titles>
  </set>
  <set>
    <titles>
      <title type="main" xml:lang="x-jat">Guskou Budori no Denki Collection</title>
    </titles>
  </set>
  <set>
    <titles>
      <title type="main" xml:lang="x-jat">Osaru no Sankichi Collection</title>
    </titles>
  </set>
  <set>
    <titles>
      <title type="main" xml:lang="x-jat">Pro Yakyuu o 10-bai Tanoshiku Miru Houhou Collection</title>
    </titles>
  </set>
  <set>
    <titles>
      <title type="main" xml:lang="x-jat">Higashi no Eden Collection</title>
      <title type="official" xml:lang="en">Eden of the East Collection</title>
    </titles>
  </set>
  <set>
    <titles>
      <title type="main" xml:lang="x-jat">Minami-ke Collection</title>
    </titles>
  </set>
  <set>
    <titles>
      <title type="main" xml:lang="x-jat">Macross F Collection</title>
      <title type="official" xml:lang="en">Macross Frontier Collection</title>
    </titles>
  </set>
  <set>
    <titles>
      <title type="main" xml:lang="x-jat">Oira Collection</title>
    </titles>
  </set>
  <set>
    <titles>
      <title type="main" xml:lang="x-jat">Tarou Collection</title>
    </titles>
  </set>
  <set>
    <titles>
      <title type="main" xml:lang="x-jat">Maabou Collection</title>
    </titles>
  </set>
  <set>
    <titles>
      <title type="main" xml:lang="x-jat">Hatanosuke Collection</title>
    </titles>
  </set>
  <set>
    <titles>
      <title type="main" xml:lang="x-jat">Ultraman Collection</title>
    </titles>
  </set>
  <set>
    <titles>
      <title type="main" xml:lang="x-jat">Byulbyul Iyagi Collection</title>
    </titles>
  </set>
  <set>
    <titles>
      <title type="main" xml:lang="x-jat">Rokudenashi Blues Collection</title>
    </titles>
  </set>
  <set>
    <titles>
      <title type="main" xml:lang="x-jat">Nansensu Monogatari Collection</title>
    </titles>
  </set>
  <set>
    <titles>
      <title type="main" xml:lang="x-jat">Chibikuro Sambo Collection</title>
    </titles>
  </set>
  <set>
    <titles>
      <title type="main" xml:lang="x-jat">Bungaku Shoujo Collection</title>
    </titles>
  </set>
  <set>
    <titles>
      <title type="main" xml:lang="x-jat">Tiger Mask Collection</title>
    </titles>
  </set>
  <set>
    <titles>
      <title type="main" xml:lang="x-jat">Nihon Manga Eiga Hattatsushi Collection</title>
    </titles>
  </set>
  <set>
    <titles>
      <title type="main" xml:lang="x-jat">Captain Collection</title>
    </titles>
  </set>
  <set>
    <titles>
      <title type="main" xml:lang="x-jat">Gintama Collection</title>
    </titles>
  </set>
  <set>
    <titles>
      <title type="main" xml:lang="x-jat">Kidou Senshi Gundam 00 Collection</title>
      <title type="official" xml:lang="en">Mobile Suit Gundam 00 Collection</title>
    </titles>
  </set>
  <set>
    <titles>
      <title type="main" xml:lang="x-jat">Toriko Collection</title>
    </titles>
  </set>
  <set>
    <titles>
      <title type="main" xml:lang="x-jat">Komaneko Collection</title>
    </titles>
  </set>
  <set>
    <titles>
      <title type="main" xml:lang="x-jat">Goulart Knights Collection</title>
    </titles>
  </set>
  <set>
    <titles>
      <title type="main" xml:lang="x-jat">Little Polar Bear Collection</title>
    </titles>
  </set>
  <set>
    <titles>
      <title type="main" xml:lang="x-jat">Kobo-chan Collection</title>
    </titles>
  </set>
  <set>
    <titles>
      <title type="main" xml:lang="x-jat">Bono Bono Collection</title>
    </titles>
  </set>
  <set>
    <titles>
      <title type="main" xml:lang="x-jat">Kaibutsu-kun Collection</title>
    </titles>
  </set>
  <set>
    <titles>
      <title type="main" xml:lang="x-jat">Obake no Q-Tarou Collection</title>
    </titles>
  </set>
  <set>
    <titles>
      <title type="main" xml:lang="x-jat">Pro Golfer Saru Collection</title>
    </titles>
  </set>
  <set>
    <titles>
      <title type="main" xml:lang="x-jat">Kyojin no Hoshi Collection</title>
      <title type="official" xml:lang="en">Star of The Giants Collection</title>
    </titles>
  </set>
  <set>
    <titles>
      <title type="main" xml:lang="x-jat">Attack No.1 Collection</title>
    </titles>
  </set>
  <set>
    <titles>
      <title type="main" xml:lang="x-jat">Alps no Shoujo Heidi Collection</title>
    </titles>
  </set>
  <set>
    <titles>
      <title type="main" xml:lang="x-jat">Inazuma Eleven Collection</title>
    </titles>
  </set>
  <set>
    <titles>
      <title type="main" xml:lang="x-jat">Hello Kitty Collection</title>
    </titles>
  </set>
  <set>
    <titles>
      <title type="main" xml:lang="x-jat">Ahiru no Pekkle Collection</title>
    </titles>
  </set>
  <set>
    <titles>
      <title type="main" xml:lang="x-jat">Pochacco Collection</title>
    </titles>
  </set>
  <set>
    <titles>
      <title type="main" xml:lang="x-jat">Bad Badtz-maru Collection</title>
    </titles>
  </set>
  <set>
    <titles>
      <title type="main" xml:lang="x-jat">Hangyodon Collection</title>
    </titles>
  </set>
  <set>
    <titles>
      <title type="main" xml:lang="x-jat">Sora no Otoshimono Collection</title>
      <title type="official" xml:lang="en">Heaven's Lost Property Collection</title>
    </titles>
  </set>
  <set>
    <titles>
      <title type="main" xml:lang="x-jat">Toaru Kagaku no Railgun Collection</title>
      <title type="official" xml:lang="en">A Certain Scientific Railgun Collection</title>
    </titles>
  </set>
  <set>
    <titles>
      <title type="main" xml:lang="x-jat">Death Note Collection</title>
    </titles>
  </set>
  <set>
    <titles>
      <title type="main" xml:lang="x-jat">Ultra Nyan Collection</title>
    </titles>
  </set>
  <set>
    <titles>
      <title type="main" xml:lang="x-jat">Hayabusa Collection</title>
    </titles>
  </set>
  <set>
    <titles>
      <title type="main" xml:lang="x-jat">Xi Yang Yang Yu Hui Tai Lang Collection</title>
    </titles>
  </set>
  <set>
    <titles>
      <title type="main" xml:lang="x-jat">Kore wa Zombie Desuka? Collection</title>
      <title type="official" xml:lang="en">Is This a Zombie? Collection</title>
    </titles>
  </set>
  <set>
    <titles>
      <title type="main" xml:lang="x-jat">Hunter x Hunter Collection</title>
    </titles>
  </set>
  <set>
    <titles>
      <title type="main" xml:lang="x-jat">Geisters: Fractions of the Earth Collection</title>
    </titles>
  </set>
  <set>
    <titles>
      <title type="main" xml:lang="x-jat">Robot Taekwon V Collection</title>
    </titles>
  </set>
  <set>
    <titles>
      <title type="main" xml:lang="x-jat">Azumanga Daiou Collection</title>
      <title type="official" xml:lang="en">Azumanga Daioh Collection</title>
    </titles>
  </set>
  <set>
    <titles>
      <title type="main" xml:lang="x-jat">Paaman Collection</title>
    </titles>
  </set>
  <set>
    <titles>
      <title type="main" xml:lang="x-jat">Uchuu Kyoudai Collection</title>
      <title type="official" xml:lang="en">Space Brothers Collection</title>
    </titles>
  </set>
  <set>
    <titles>
      <title type="main" xml:lang="x-jat">Short Peace Collection</title>
    </titles>
  </set>
  <set>
    <titles>
      <title type="main" xml:lang="x-jat">Persona Collection</title>
    </titles>
  </set>
  <set>
    <titles>
      <title type="main" xml:lang="x-jat">Shimajirou Collection</title>
    </titles>
  </set>
  <set>
    <titles>
      <title type="main" xml:lang="x-jat">Sonyeon 007 Collection</title>
    </titles>
  </set>
  <set>
    <titles>
      <title type="main" xml:lang="x-jat">Date a Live Collection</title>
    </titles>
  </set>
  <set>
    <titles>
      <title type="main" xml:lang="x-jat">Yowamushi Pedal Collection</title>
    </titles>
  </set>
  <set>
    <titles>
      <title type="main" xml:lang="x-jat">Natsume Yuujinchou Collection</title>
      <title type="official" xml:lang="en">Natsume's Book of Friends Collection</title>
    </titles>
  </set>
  <set>
    <titles>
      <title type="main" xml:lang="x-jat">Zukkoke Sanningumi Collection</title>
    </titles>
  </set>
  <set>
    <titles>
      <title type="main" xml:lang="x-jat">Girls und Panzer Collection</title>
    </titles>
  </set>
  <set>
    <titles>
      <title type="main" xml:lang="x-jat">Mushishi Collection</title>
      <title type="official" xml:lang="en">Mushi-Shi Collection</title>
    </titles>
  </set>
</anime-set-list>